gclick_sdk/__init__.py
gclick_sdk/atividade_exception.py
gclick_sdk/atividades_client.py
gclick_sdk/credentials.py
gclick_sdk/exception.py
gclick_sdk/gclick.py
gclick_sdk-0.0.3.dist-info/LICENSE
gclick_sdk-0.0.3.dist-info/METADATA
gclick_sdk-0.0.3.dist-info/WHEEL
gclick_sdk-0.0.3.dist-info/top_level.txt
gclick_sdk-0.0.3.dist-info/RECORD
