Metadata-Version: 2.1
Name: gclick-sdk
Version: 0.0.3
Summary: SDK Python para integração com a plataforma de controle de processos GClick.
Home-page: https://github.com/Nasajon/gclick_sdk
Author: Nasajon Sistemas
Author-email: contact.dev@nasajon.com.br
License: UNKNOWN
Project-URL: Source, https://github.com/Nasajon/gclick_sdk
Platform: UNKNOWN
Classifier: Development Status :: 3 - Alpha
Classifier: Intended Audience :: Developers
Classifier: Topic :: Software Development :: Build Tools
Classifier: Programming Language :: Python :: 3
Requires-Python: >=3.4
License-File: LICENSE
